mylib017/__init__.py
mylib017-0.1.dist-info/LICENSE.txt.txt
mylib017-0.1.dist-info/METADATA
mylib017-0.1.dist-info/WHEEL
mylib017-0.1.dist-info/top_level.txt
mylib017-0.1.dist-info/RECORD
