Metadata-Version: 2.1
Name: mylib017
Version: 0.1
Summary: For calculating square of a number
Author: Jaideep
Author-email: dajaideep@gmail.com
Classifier: Programming Language :: Python :: 3
Classifier: License :: OSI Approved :: MIT License
Classifier: Operating System :: OS Independent
License-File: LICENSE.txt.txt
